springy/__init__.py
springy/apps.py
springy/connections.py
springy/exceptions.py
springy/fields.py
springy/helpers.py
springy/indices.py
springy/schema.py
springy/search.py
springy/settings.py
springy/utils.py
springy/management/__init__.py
springy/management/commands/__init__.py
springy/management/commands/index.py
springy-5.0.1.dist-info/DESCRIPTION.rst
springy-5.0.1.dist-info/METADATA
springy-5.0.1.dist-info/RECORD
springy-5.0.1.dist-info/WHEEL
springy-5.0.1.dist-info/dependency_links.txt
springy-5.0.1.dist-info/metadata.json
springy-5.0.1.dist-info/top_level.txt
tests/__init__.py
tests/test_indices.py
