Metadata-Version: 2.0
Name: springy
Version: 5.0.1
Summary: An elasticsearch wrapper for Django
Home-page: https://github.com/marcinn/springy
Author: Marcin Nowak
Author-email: marcin.j.nowak@gmail.com
License: BSD
Keywords: elasticsearch django springy
Platform: UNKNOWN
Classifier: Development Status :: 2 - Pre-Alpha
Classifier: Intended Audience :: Developers
Classifier: License :: OSI Approved :: BSD License
Classifier: Environment :: Web Environment
Classifier: Operating System :: OS Independent
Classifier: Programming Language :: Python :: 2
Classifier: Programming Language :: Python :: 2.7
Classifier: Programming Language :: Python :: 3
Classifier: Programming Language :: Python :: 3.5
Classifier: Programming Language :: Python :: 3.6
Classifier: Framework :: Django
Classifier: Framework :: Django :: 1.7
Classifier: Framework :: Django :: 1.8
Classifier: Framework :: Django :: 1.9
Classifier: Framework :: Django :: 1.10
Classifier: Framework :: Django :: 1.11
Classifier: Topic :: Text Processing :: Indexing
Requires-Dist: elasticsearch-dsl (>=5.0.0)
Requires-Dist: six
